djangocms_unitegallery/__init__.py
djangocms_unitegallery/admin.py
djangocms_unitegallery/cms_plugins.py
djangocms_unitegallery/models.py
djangocms_unitegallery/settings.py
djangocms_unitegallery/locale/en/LC_MESSAGES/django.mo
djangocms_unitegallery/locale/en/LC_MESSAGES/django.po
djangocms_unitegallery/locale/fr/LC_MESSAGES/django.mo
djangocms_unitegallery/locale/fr/LC_MESSAGES/django.po
djangocms_unitegallery/migrations/0001_initial.py
djangocms_unitegallery/migrations/__init__.py
djangocms_unitegallery/static/djangocms_unitegallery/unitegallery/css/unite-gallery.css
djangocms_unitegallery/static/djangocms_unitegallery/unitegallery/images/button-close.png
djangocms_unitegallery/static/djangocms_unitegallery/unitegallery/images/cover-grid.png
djangocms_unitegallery/static/djangocms_unitegallery/unitegallery/images/icon-link32.png
djangocms_unitegallery/static/djangocms_unitegallery/unitegallery/images/icon-play32.png
djangocms_unitegallery/static/djangocms_unitegallery/unitegallery/images/icon-zoom32.png
djangocms_unitegallery/static/djangocms_unitegallery/unitegallery/images/lightbox-arrow-left.png
djangocms_unitegallery/static/djangocms_unitegallery/unitegallery/images/lightbox-arrow-right.png
djangocms_unitegallery/static/djangocms_unitegallery/unitegallery/images/lightbox-icon-close-compact.png
djangocms_unitegallery/static/djangocms_unitegallery/unitegallery/images/lightbox-icon-close-compact2.png
djangocms_unitegallery/static/djangocms_unitegallery/unitegallery/images/lightbox-icon-close.png
djangocms_unitegallery/static/djangocms_unitegallery/unitegallery/images/loader-black1.gif
djangocms_unitegallery/static/djangocms_unitegallery/unitegallery/images/loader-black2.gif
djangocms_unitegallery/static/djangocms_unitegallery/unitegallery/images/loader-black3.gif
djangocms_unitegallery/static/djangocms_unitegallery/unitegallery/images/loader-black4.gif
djangocms_unitegallery-0.1.0.dist-info/DESCRIPTION.rst
djangocms_unitegallery-0.1.0.dist-info/METADATA
djangocms_unitegallery-0.1.0.dist-info/RECORD
djangocms_unitegallery-0.1.0.dist-info/WHEEL
djangocms_unitegallery-0.1.0.dist-info/metadata.json
djangocms_unitegallery-0.1.0.dist-info/top_level.txt
