Metadata-Version: 2.0
Name: djangocms-unitegallery
Version: 0.1.0
Summary: unitegallery grid Plugin for django CMS
Home-page: https://github.com/izimobil/djangocms-unitegallery
Author: David Jean Louis
Author-email: izimobil@gmail.com
License: LICENSE.txt
Platform: OS Independent
Classifier: Development Status :: 4 - Beta
Classifier: Environment :: Web Environment
Classifier: Framework :: Django
Classifier: Intended Audience :: Developers
Classifier: License :: OSI Approved :: MIT License
Classifier: Operating System :: OS Independent
Classifier: Topic :: Internet :: WWW/HTTP :: Dynamic Content
Classifier: Topic :: Software Development
Classifier: Topic :: Software Development :: Libraries :: Application Frameworks
Classifier: Programming Language :: Python
Classifier: Programming Language :: Python :: 2.7
Classifier: Programming Language :: Python :: 3.3
Classifier: Programming Language :: Python :: 3.4
Classifier: Programming Language :: Python :: 3.5
Classifier: Framework :: Django
Classifier: Framework :: Django :: 1.7
Classifier: Framework :: Django :: 1.8
Classifier: Framework :: Django :: 1.9
Requires-Dist: django (>=1.7)
Requires-Dist: django-cms (>=3.0)
Requires-Dist: sorl-thumbnail (>=12.0)
